omz_theme_ignore/__init__.py
omz_theme_ignore/main.py
omz_theme_ignore-0.1.3.dist-info/entry_points.txt
omz_theme_ignore-0.1.3.dist-info/WHEEL
omz_theme_ignore-0.1.3.dist-info/METADATA
omz_theme_ignore-0.1.3.dist-info/RECORD
